LICENSE.md
README.md
setup.py
pykraken2/__init__.py
pykraken2/client.py
pykraken2/server.py
pykraken2.egg-info/PKG-INFO
pykraken2.egg-info/SOURCES.txt
pykraken2.egg-info/dependency_links.txt
pykraken2.egg-info/entry_points.txt
pykraken2.egg-info/not-zip-safe
pykraken2.egg-info/requires.txt
pykraken2.egg-info/top_level.txt