Metadata-Version: 2.1
Name: pykraken2
Version: 0.0.1
Summary: kraken2 server/client implementation in Python
Home-page: https://github.com/epi2me-labs/pykraken2
Author: nhorner
Author-email: nhorner@nanoporetech.com
License-File: LICENSE.md
